gcm_filters/__init__.py
gcm_filters/_version.py
gcm_filters/filter.py
gcm_filters/gpu_compat.py
gcm_filters/kernels.py
tests/__init__.py
tests/conftest.py
tests/test_filter.py
tests/test_filter_validation.py
tests/test_kernels.py
tests/test_kernels_validation.py
gcm_filters-0.5.1.dist-info/LICENSE.txt
gcm_filters-0.5.1.dist-info/METADATA
gcm_filters-0.5.1.dist-info/WHEEL
gcm_filters-0.5.1.dist-info/top_level.txt
gcm_filters-0.5.1.dist-info/RECORD
