Metadata-Version: 2.1
Name: gcm_filters
Version: 0.5.1
Summary: Diffusion-based Spatial Filtering of Gridded Data
Home-page: https://github.com/ocean-eddy-cpt/gcm-filters
Author: Ocean Eddy CPT Team
Author-email: nora.loose@gmail.com
License: LGPL-3.0
Classifier: Development Status :: 5 - Production/Stable
Classifier: Intended Audience :: Science/Research
Classifier: Operating System :: OS Independent
Classifier: License :: OSI Approved :: GNU Lesser General Public License v3 (LGPLv3)
Classifier: Programming Language :: Python
Classifier: Programming Language :: Python :: 3
Classifier: Programming Language :: Python :: 3.10
Classifier: Programming Language :: Python :: 3.11
Classifier: Programming Language :: Python :: 3.12
Classifier: Topic :: Scientific/Engineering
Requires-Python: >=3.9
License-File: LICENSE.txt
Requires-Dist: numpy
Requires-Dist: xarray
Requires-Dist: scipy
Requires-Dist: matplotlib
